sferriol/python/__init__.py
sferriol/python/asyncio.py
sferriol/python/env.py
sferriol/python/json.py
sferriol/python/net.py
sferriol/python/object.py
sferriol/python/os_.py
sferriol/python/pkg.py
sferriol/python/dictionary/__init__.py
sferriol/python/test/pkg/__init__.py
sferriol/python/test/pkg/toto.py
sferriol/python/test/pkg/tutu.py
sferriol_python-0.8.1.dist-info/licenses/LICENSE
sferriol_python-0.8.1.dist-info/METADATA
sferriol_python-0.8.1.dist-info/WHEEL
sferriol_python-0.8.1.dist-info/top_level.txt
sferriol_python-0.8.1.dist-info/RECORD
