Metadata-Version: 2.4
Name: sferriol-python
Version: 0.8.1
Summary: python utilities
Home-page: https://gitlab.in2p3.fr/sferriol-ip2i/sferriol-python
Author: Sylvain Ferriol
Author-email: s.ferriol@ipnl.in2p3.fr
Classifier: License :: OSI Approved :: The Unlicense (Unlicense)
Classifier: Operating System :: OS Independent
Classifier: Programming Language :: Python :: 3
License-File: LICENSE
Provides-Extra: dev
Requires-Dist: click; extra == "dev"
Requires-Dist: yapf; extra == "dev"
Dynamic: license-file
